{
  "info": {
    "name": "MatrizCompetencia",
    "schema": "https://schema.getpostman.com/json/collection/v2.1.0/collection.json"
  },
  "item": [
    {
      "name": "Users",
      "item": [
        {
          "name": "postCreateUser",
          "request": {
            "method": "POST",
            "header": [],
            "auth": {
              "type": "noauth"
            },
            "description": "",
            "url": {
              "raw": "http://localhost:3000/users",
              "protocol": "http",
              "host": [
                "localhost:3000"
              ],
              "path": [
                "users"
              ],
              "query": [],
              "variable": []
            },
            "body": {
              "mode": "raw",
              "raw": "{\"name\":\"Luiz Felipe\",\n \"email\":\"IchigoArndt@gmail.com\"\n}",
              "options": {
                "raw": {
                  "language": "json"
                }
              }
            }
          }
        },
        {
          "name": "GetUsers",
          "request": {
            "method": "GET",
            "header": [],
            "auth": {
              "type": "noauth"
            },
            "description": "",
            "url": {
              "raw": "http://localhost:3000/users",
              "protocol": "http",
              "host": [
                "localhost:3000"
              ],
              "path": [
                "users"
              ],
              "query": [],
              "variable": []
            }
          }
        },
        {
          "name": "GetUserById",
          "request": {
            "method": "GET",
            "header": [],
            "auth": {
              "type": "noauth"
            },
            "description": "",
            "url": {
              "raw": "http://localhost:3000/users/1",
              "protocol": "http",
              "host": [
                "localhost:3000"
              ],
              "path": [
                "users",
                "1"
              ],
              "query": [],
              "variable": []
            }
          }
        },
        {
          "name": "PutUser",
          "request": {
            "method": "PUT",
            "header": [],
            "auth": {
              "type": "noauth"
            },
            "description": "",
            "url": {
              "raw": "http://localhost:3000/users/1",
              "protocol": "http",
              "host": [
                "localhost:3000"
              ],
              "path": [
                "users",
                "1"
              ],
              "query": [],
              "variable": []
            },
            "body": {
              "mode": "raw",
              "raw": "{\n  \"name\":\"Luiz Felipe\"\n}",
              "options": {
                "raw": {
                  "language": "json"
                }
              }
            }
          }
        },
        {
          "name": "DeleteUser",
          "request": {
            "method": "DELETE",
            "header": [],
            "auth": {
              "type": "noauth"
            },
            "description": "",
            "url": {
              "raw": "http://localhost:3000/users/1",
              "protocol": "http",
              "host": [
                "localhost:3000"
              ],
              "path": [
                "users",
                "1"
              ],
              "query": [],
              "variable": []
            }
          }
        }
      ]
    },
    {
      "name": "Conversions",
      "item": [
        {
          "name": "CreateConversion",
          "request": {
            "method": "POST",
            "header": [],
            "auth": {
              "type": "noauth"
            },
            "description": "",
            "url": {
              "raw": "http://localhost:3000/conversion-history",
              "protocol": "http",
              "host": [
                "localhost:3000"
              ],
              "path": [
                "conversion-history"
              ],
              "query": [],
              "variable": []
            },
            "body": {
              "mode": "raw",
              "raw": "{\n  \"userId\": 2,\n  \"inputValue\": \"4095\",\n  \"fromBase\": 10,\n  \"toBase\": 64\n}",
              "options": {
                "raw": {
                  "language": "json"
                }
              }
            }
          }
        },
        {
          "name": "GetConversionByUserId",
          "request": {
            "method": "GET",
            "header": [],
            "auth": {
              "type": "noauth"
            },
            "description": "",
            "url": {
              "raw": "http://localhost:3000/conversion-history/user/2",
              "protocol": "http",
              "host": [
                "localhost:3000"
              ],
              "path": [
                "conversion-history",
                "user",
                "2"
              ],
              "query": [],
              "variable": []
            }
          }
        },
        {
          "name": "GetAllConversions",
          "request": {
            "method": "GET",
            "header": [],
            "auth": {
              "type": "noauth"
            },
            "description": "",
            "url": {
              "raw": "http://localhost:3000/conversion-history",
              "protocol": "http",
              "host": [
                "localhost:3000"
              ],
              "path": [
                "conversion-history"
              ],
              "query": [],
              "variable": []
            }
          }
        },
        {
          "name": "GetByConversionId",
          "request": {
            "method": "GET",
            "header": [],
            "auth": {
              "type": "noauth"
            },
            "description": "",
            "url": {
              "raw": "http://localhost:3000/conversion-history/2",
              "protocol": "http",
              "host": [
                "localhost:3000"
              ],
              "path": [
                "conversion-history",
                "2"
              ],
              "query": [],
              "variable": []
            }
          }
        },
        {
          "name": "DeleteConversionHistory",
          "request": {
            "method": "DELETE",
            "header": [],
            "auth": {
              "type": "noauth"
            },
            "description": "",
            "url": {
              "raw": "http://localhost:3000/conversion-history/1",
              "protocol": "http",
              "host": [
                "localhost:3000"
              ],
              "path": [
                "conversion-history",
                "1"
              ],
              "query": [],
              "variable": []
            }
          }
        },
        {
          "name": "PutConversionHistory",
          "request": {
            "method": "PUT",
            "header": [],
            "auth": {
              "type": "noauth"
            },
            "description": "",
            "url": {
              "raw": "http://localhost:3000/conversion-history/2",
              "protocol": "http",
              "host": [
                "localhost:3000"
              ],
              "path": [
                "conversion-history",
                "2"
              ],
              "query": [],
              "variable": []
            },
            "body": {
              "mode": "raw",
              "raw": "{\n  \"userId\":\"2\",\n  \"inputValue\":\"20\"\n}",
              "options": {
                "raw": {
                  "language": "json"
                }
              }
            }
          }
        },
        {
          "name": "PatchConversionHistory",
          "request": {
            "method": "PATCH",
            "header": [],
            "auth": {
              "type": "noauth"
            },
            "description": "",
            "url": {
              "raw": "http://localhost:3000/conversion-history/2",
              "protocol": "http",
              "host": [
                "localhost:3000"
              ],
              "path": [
                "conversion-history",
                "2"
              ],
              "query": [],
              "variable": []
            },
            "body": {
              "mode": "raw",
              "raw": "{\n  \"id\": 2,\n  \"userId\": 2,\n  \"inputValue\": \"30\",\n  \"fromBase\": 10,\n  \"toBase\": 16\n}",
              "options": {
                "raw": {
                  "language": "json"
                }
              }
            }
          }
        }
      ]
    }
  ],
  "variable": []
}